ghulda/__init__.py
ghulda/model.py
ghulda/preprocessing.py
ghulda-1.1.1.dist-info/METADATA
ghulda-1.1.1.dist-info/WHEEL
ghulda-1.1.1.dist-info/top_level.txt
ghulda-1.1.1.dist-info/RECORD
