Metadata-Version: 2.4
Name: GhuLDA
Version: 1.1.1
Summary: Pacote com funções para processamento de modelos LDA
Home-page: https://github.com/ghurone/ghulab
Author: Erick Ghuron
Author-email: ghuron@usp.br
License: MIT
Keywords: ghu,lda
Classifier: Intended Audience :: Developers
Classifier: License :: OSI Approved :: MIT License
Classifier: Programming Language :: Python :: 3
Requires-Dist: gensim==4.3.3
Requires-Dist: spacy==3.7.5
Requires-Dist: tqdm>=4.66.1
Dynamic: author
Dynamic: author-email
Dynamic: classifier
Dynamic: description
Dynamic: description-content-type
Dynamic: home-page
Dynamic: keywords
Dynamic: license
Dynamic: requires-dist
Dynamic: summary
